populationDescent/__init__.py
populationDescent/populationDescent.py
populationDescent-0.0.1.dist-info/LICENSE
populationDescent-0.0.1.dist-info/METADATA
populationDescent-0.0.1.dist-info/WHEEL
populationDescent-0.0.1.dist-info/top_level.txt
populationDescent-0.0.1.dist-info/RECORD
