Metadata-Version: 2.1
Name: populationDescent
Version: 0.0.1
Summary: global optimization
Author-email: "Abhi Pomalapally, Bassel Mabsout" <abhinav_pomalapally@berkeley.edu>
Project-URL: Homepage, https://github.com/abhi0220/populationDescent
Classifier: Programming Language :: Python :: 3
Classifier: License :: OSI Approved :: MIT License
Classifier: Operating System :: OS Independent
Requires-Python: >=3.9
License-File: LICENSE
